openmock/__init__.py
openmock/fake_asyncindices.py
openmock/fake_asyncopensearch.py
openmock/fake_cluster.py
openmock/fake_indices.py
openmock/fake_opensearch.py
openmock/normalize_hosts.py
openmock/behaviour/__init__.py
openmock/behaviour/server_failure.py
openmock/utilities/__init__.py
openmock/utilities/decorator.py
openmock-3.1.5.dist-info/METADATA
openmock-3.1.5.dist-info/WHEEL
openmock-3.1.5.dist-info/licenses/LICENSE
openmock-3.1.5.dist-info/RECORD
