Metadata-Version: 2.4
Name: openmock
Version: 3.1.5
Summary: Python OpenSearch Mock for test purposes
Project-URL: Bug Tracker, https://github.com/matthewdeanmartin/openmock/issues
Project-URL: Change Log, https://github.com/matthewdeanmartin/openmock/blob/main/CHANGELOG.md
Author: Marcos Cardoso
Author-email: Mathew Martin <matthewdeanmartin@gmail.com>
License: MIT
License-File: LICENSE
Keywords: mocking,opensearch,testing
Classifier: Environment :: Web Environment
Classifier: Intended Audience :: Developers
Classifier: License :: OSI Approved :: MIT License
Classifier: Operating System :: OS Independent
Classifier: Programming Language :: Python
Classifier: Programming Language :: Python :: 3.10
Classifier: Programming Language :: Python :: 3.11
Classifier: Programming Language :: Python :: 3.12
Classifier: Programming Language :: Python :: 3.13
Classifier: Programming Language :: Python :: 3.14
Classifier: Topic :: Software Development :: Libraries :: Python Modules
Requires-Python: >=3.10
Requires-Dist: aiohttp
Requires-Dist: opensearch-py
Requires-Dist: python-dateutil>=2.8.2
Requires-Dist: python-ranges==0.2.1
